{
  "app": {
    "version": "6.1.1-2018120801-ianmacd",
    "versionCode": "2018120801",
    "link": "https://github.com/ianmacd/MagiskBuilds/raw/master/MagiskManager-v6.1.1-2018120801-ianmacd.apk"
  },
  "magisk": {
    "version": "18.1-2018120801-ianmacd",
    "versionCode": "2018120801",
    "link": "https://github.com/ianmacd/MagiskBuilds/raw/master/Magisk-v18.1-2018120801-ianmacd.zip",
    "note": "https://forum.xda-developers.com/showthread.php?t=3521901",
    "md5": "d8377f05e2c235396baba11d11deb68e"
  },
  "uninstaller": {
    "link": "https://github.com/ianmacd/MagiskBuilds/raw/master/Magisk-uninstaller-v18.1-2018120801-ianmacd.zip"
  },
  "snet": {
    "versionCode": "12",
    "link": "https://github.com/ianmacd/MagiskBuilds/raw/master/snet.apk"
  }
}
