{
  "app": {
    "version": "6.1.1-2019020402-ianmacd",
    "versionCode": "2019020402",
    "link": "https://github.com/ianmacd/MagiskBuilds/raw/testing/MagiskManager-v6.1.1-2019020402-ianmacd.apk"
  },
  "magisk": {
    "version": "18.1-2019020402-ianmacd",
    "versionCode": "2019020402",
    "link": "https://github.com/ianmacd/MagiskBuilds/raw/testing/Magisk-v18.1-2019020402-ianmacd.zip",
    "note": "https://forum.xda-developers.com/showthread.php?t=3521901",
    "md5": "360625dd781138ace79ecdc5de69ff53"
  },
  "uninstaller": {
    "link": "https://github.com/ianmacd/MagiskBuilds/raw/testing/Magisk-uninstaller-v18.1-2019020402-ianmacd.zip"
  },
  "snet": {
    "versionCode": "12",
    "link": "https://github.com/ianmacd/MagiskBuilds/raw/testing/snet.apk"
  }
}
